easyfit/__init__.py
easyfit/_models.py
easyfit/classifiers.py
easyfit/exceptions.py
easyfit/regressors.py
easyfit-0.0.21.dist-info/LICENSE
easyfit-0.0.21.dist-info/METADATA
easyfit-0.0.21.dist-info/WHEEL
easyfit-0.0.21.dist-info/top_level.txt
easyfit-0.0.21.dist-info/RECORD
